optype/__init__.py
optype/__init__.pyi
optype/_core/__init__.py
optype/_core/_can.py
optype/_core/_do.py
optype/_core/_does.py
optype/_core/_has.py
optype/_core/_just.py
optype/_utils.py
optype/copy.py
optype/dataclasses.py
optype/dlpack.py
optype/inspect.py
optype/io.py
optype/json.py
optype/numpy/__init__.py
optype/numpy/_any_array.py
optype/numpy/_any_dtype.py
optype/numpy/_array.py
optype/numpy/_ctypeslib.py
optype/numpy/_ctypeslib.pyi
optype/numpy/_dtype.py
optype/numpy/_dtype_attr.py
optype/numpy/_is.py
optype/numpy/_literals.py
optype/numpy/_scalar.py
optype/numpy/_sequence_nd.py
optype/numpy/_shape.py
optype/numpy/_to.py
optype/numpy/_ufunc.py
optype/numpy/compat.py
optype/numpy/ctypeslib.py
optype/numpy/random.py
optype/pickle.py
optype/py.typed
optype/string.py
optype/types/__init__.py
optype/types/_typeforms.py
optype/types/_typeforms.pyi
optype/typing.py
optype-0.13.2.dist-info/licenses/LICENSE
optype-0.13.2.dist-info/WHEEL
optype-0.13.2.dist-info/METADATA
optype-0.13.2.dist-info/RECORD
